AdsorptionBreakthroughAnalysis/__init__.py
AdsorptionBreakthroughAnalysis/__main__.py
AdsorptionBreakthroughAnalysis/api.py
AdsorptionBreakthroughAnalysis/breakthrough_analysis.py
AdsorptionBreakthroughAnalysis/cli.py
AdsorptionBreakthroughAnalysis/py.typed
AdsorptionBreakthroughAnalysis/version.py
AdsorptionBreakthroughAnalysis-0.0.3.dist-info/LICENSE
AdsorptionBreakthroughAnalysis-0.0.3.dist-info/METADATA
AdsorptionBreakthroughAnalysis-0.0.3.dist-info/WHEEL
AdsorptionBreakthroughAnalysis-0.0.3.dist-info/entry_points.txt
AdsorptionBreakthroughAnalysis-0.0.3.dist-info/top_level.txt
AdsorptionBreakthroughAnalysis-0.0.3.dist-info/RECORD
