Metadata-Version: 2.1
Name: AdsorptionBreakthroughAnalysis
Version: 0.0.3
Summary: This program is used to analyse the breakthrough curves generated by the RCCS adsorption rig
Home-page: https://github.com/RCCS-CaptureTeam/Adsorption_Breakthrough_Analysis
Download-URL: https://github.com/RCCS-CaptureTeam/Adsorption_Breakthrough_Analysis/releases
Author: Daniel Maroto-Andresen
Author-email: dm937@cam.ac.uk
Maintainer: Fergus Mcilwaine
Maintainer-email: f.mcilwaine@hw.ac.uk
License: MIT
Project-URL: Bug Tracker, https://github.com/RCCS-CaptureTeam/Adsorption_Breakthrough_Analysis/issues
Project-URL: Source Code, https://github.com/RCCS-CaptureTeam/Adsorption_Breakthrough_Analysis
Keywords: snekpack,cookiecutter
Classifier: Development Status :: 1 - Planning
Classifier: Environment :: Console
Classifier: Intended Audience :: Developers
Classifier: License :: OSI Approved :: MIT License
Classifier: Operating System :: OS Independent
Classifier: Framework :: Pytest
Classifier: Framework :: tox
Classifier: Framework :: Sphinx
Classifier: Programming Language :: Python
Classifier: Programming Language :: Python :: 3.8
Classifier: Programming Language :: Python :: 3.9
Classifier: Programming Language :: Python :: 3.10
Classifier: Programming Language :: Python :: 3.11
Classifier: Programming Language :: Python :: 3 :: Only
Requires-Python: >=3.8
License-File: LICENSE
Requires-Dist: more-itertools
Requires-Dist: tqdm
Requires-Dist: click
Requires-Dist: more-click
Requires-Dist: pandas
Requires-Dist: seaborn
Requires-Dist: matplotlib
Requires-Dist: scipy
Provides-Extra: docs
Requires-Dist: sphinx ; extra == 'docs'
Requires-Dist: sphinx-rtd-theme ; extra == 'docs'
Requires-Dist: sphinx-click ; extra == 'docs'
Requires-Dist: sphinx-autodoc-typehints ; extra == 'docs'
Requires-Dist: sphinx-automodapi ; extra == 'docs'
Provides-Extra: tests
Requires-Dist: pytest ; extra == 'tests'
Requires-Dist: coverage ; extra == 'tests'
